liang/__init__.py
liang/environment.py
liang/errors.py
liang/handlers.py
liang/latency.py
liang/main.py
liang/measurement.py
liang/utils.py
python_liang-0.0.3.dist-info/LICENSE
python_liang-0.0.3.dist-info/METADATA
python_liang-0.0.3.dist-info/WHEEL
python_liang-0.0.3.dist-info/top_level.txt
python_liang-0.0.3.dist-info/RECORD
