Metadata-Version: 2.1
Name: python-liang
Version: 0.0.3
Summary: Incorporate non-functional requirements in function definitions
Home-page: https://github.com/yizhang7210/liang
Author: Yi Zhang
Author-email: yi.zhang7210@gmail.com
License: MIT
Platform: UNKNOWN
Classifier: License :: OSI Approved :: MIT License
Classifier: Programming Language :: Python :: 3
Classifier: Programming Language :: Python :: 3.8
License-File: LICENSE
Requires-Dist: numpy
